ahocorasick/__init__.py
ahocorasick/core.py
ackit-0.1.2.dist-info/LICENSE
ackit-0.1.2.dist-info/METADATA
ackit-0.1.2.dist-info/WHEEL
ackit-0.1.2.dist-info/top_level.txt
ackit-0.1.2.dist-info/RECORD
