Metadata-Version: 2.1
Name: ackit
Version: 0.1.2
Summary: simple and pure python package and like pyahocorasick.
Home-page: https://github.com/KuangDD/ackit
Author: kuangdd
Author-email: kuangdd@foxmail.com
License: UNKNOWN
Platform: UNKNOWN
Classifier: Intended Audience :: Developers
Classifier: Topic :: Software Development :: Build Tools
Classifier: License :: OSI Approved :: MIT License
Classifier: Programming Language :: Python :: 3.5
Classifier: Programming Language :: Python :: 3.6
Classifier: Programming Language :: Python :: 3.7
Classifier: Programming Language :: Python :: 3.8
Classifier: Programming Language :: Python :: 3.9
Classifier: Operating System :: OS Independent
Requires-Python: >=3.5
